{
 "stats": {
  "Singapore P6": {
   "gold": 1,
   "matched": 1,
   "NOT_IN_CORPUS": 0,
   "IN_CORPUS_NOT_EMITTED": 0,
   "EMITTED_OTHER_INDICATOR": 0,
   "GOLD_REF_UNPARSEABLE": 0
  },
  "Singapore P7": {
   "gold": 6,
   "matched": 6,
   "NOT_IN_CORPUS": 0,
   "IN_CORPUS_NOT_EMITTED": 0,
   "EMITTED_OTHER_INDICATOR": 0,
   "GOLD_REF_UNPARSEABLE": 0
  },
  "Malaysia P6": {
   "gold": 9,
   "matched": 2,
   "NOT_IN_CORPUS": 5,
   "IN_CORPUS_NOT_EMITTED": 2,
   "EMITTED_OTHER_INDICATOR": 0,
   "GOLD_REF_UNPARSEABLE": 0
  },
  "Malaysia P7": {
   "gold": 12,
   "matched": 11,
   "NOT_IN_CORPUS": 1,
   "IN_CORPUS_NOT_EMITTED": 0,
   "EMITTED_OTHER_INDICATOR": 0,
   "GOLD_REF_UNPARSEABLE": 0
  },
  "Australia P6": {
   "gold": 1,
   "matched": 1,
   "NOT_IN_CORPUS": 0,
   "IN_CORPUS_NOT_EMITTED": 0,
   "EMITTED_OTHER_INDICATOR": 0,
   "GOLD_REF_UNPARSEABLE": 0
  },
  "Australia P7": {
   "gold": 4,
   "matched": 4,
   "NOT_IN_CORPUS": 0,
   "IN_CORPUS_NOT_EMITTED": 0,
   "EMITTED_OTHER_INDICATOR": 0,
   "GOLD_REF_UNPARSEABLE": 0
  }
 },
 "misses": [
  {
   "economy": "Malaysia",
   "pillar": "6",
   "run": "outputs/final_ma_p6",
   "gold_indicator": "P6-I4",
   "act": "Personal Data Protection Act (Act 709) 2010;\n\nPersonal Data Protection\n(Amendment) Bill (Act A1727) 2024",
   "ref": "s. 4.11",
   "base": "s. 4.11",
   "class": "STRUCTURE",
   "emitted_under": [],
   "proposed_verdict": "REAL_MISS",
   "evidence": {
    "corpus_checked": true,
    "matched_output_rows": 0,
    "technical_class": "NOT_IN_CORPUS",
    "failure_taxonomy": "STRUCTURE"
   },
   "reviewer_verdict": "GOLD_WRONG",
   "reviewer_note": "Act 709 contains no decimal-numbered clause 4.11; CoP-style numbering misattributed to the Act (planted-error class).",
   "recall_key": "be0d1cc89ca4f580416bf8667888ec5351be3b96f20df355f344e0a156fceebb",
   "review": {
    "recall_key": "be0d1cc89ca4f580416bf8667888ec5351be3b96f20df355f344e0a156fceebb",
    "verdict": "GOLD_WRONG",
    "reviewer_name": "Abu Naser Md. Nafew",
    "reviewer_role": "Team Lead, Team zAI BD",
    "reviewed_at": "2026-07-19T12:50:04+00:00",
    "note": "Act 709 contains no decimal-numbered clause 4.11; CoP-style numbering misattributed to the Act (planted-error class)."
   }
  },
  {
   "economy": "Malaysia",
   "pillar": "6",
   "run": "outputs/final_ma_p6",
   "gold_indicator": "P6-I4",
   "act": "Personal Data Protection Act (Act 709) 2010;\n\nPersonal Data Protection\n(Amendment) Bill (Act A1727) 2024",
   "ref": "s. 1.1(38)",
   "base": "s. 1.1",
   "class": "MAPPING",
   "emitted_under": [],
   "proposed_verdict": "LEGAL_MAPPING_REVIEW",
   "evidence": {
    "corpus_checked": true,
    "matched_output_rows": 0,
    "technical_class": "IN_CORPUS_NOT_EMITTED",
    "failure_taxonomy": "MAPPING"
   },
   "reviewer_verdict": "GOLD_WRONG",
   "reviewer_note": "'s. 1.1(38)' is a Code of Practice definitions clause, not an Act provision; misattributed citation.",
   "recall_key": "ea7a3726a61583f3335a5856dd2ab4c4740ed1bf9936dbc6393f362eef8dd7af",
   "review": {
    "recall_key": "ea7a3726a61583f3335a5856dd2ab4c4740ed1bf9936dbc6393f362eef8dd7af",
    "verdict": "GOLD_WRONG",
    "reviewer_name": "Abu Naser Md. Nafew",
    "reviewer_role": "Team Lead, Team zAI BD",
    "reviewed_at": "2026-07-19T12:50:04+00:00",
    "note": "'s. 1.1(38)' is a Code of Practice definitions clause, not an Act provision; misattributed citation."
   }
  },
  {
   "economy": "Malaysia",
   "pillar": "6",
   "run": "outputs/final_ma_p6",
   "gold_indicator": "P6-I4",
   "act": "Personal Data Protection Act (Act 709) 2010;\n\nPersonal Data Protection\n(Amendment) Bill (Act A1727) 2024",
   "ref": "Sch. 1",
   "base": "sch. 1",
   "class": "STRUCTURE",
   "emitted_under": [],
   "proposed_verdict": "REAL_MISS",
   "evidence": {
    "corpus_checked": true,
    "matched_output_rows": 0,
    "technical_class": "NOT_IN_CORPUS",
    "failure_taxonomy": "STRUCTURE"
   },
   "reviewer_verdict": "GOLD_AMBIGUOUS",
   "reviewer_note": "Act 709 Schedule 1 exists but the master's link to P6-I4 is unverifiable from its prose; [verify] \u2014 to be resolved in tonight's rerun.",
   "recall_key": "739c90b6df20932e99e271950e58b41e7ad89bd7fafe533b1bcd32eaa0bb85c4",
   "review": {
    "recall_key": "739c90b6df20932e99e271950e58b41e7ad89bd7fafe533b1bcd32eaa0bb85c4",
    "verdict": "GOLD_AMBIGUOUS",
    "reviewer_name": "Abu Naser Md. Nafew",
    "reviewer_role": "Team Lead, Team zAI BD",
    "reviewed_at": "2026-07-19T12:50:04+00:00",
    "note": "Act 709 Schedule 1 exists but the master's link to P6-I4 is unverifiable from its prose; [verify] \u2014 to be resolved in tonight's rerun."
   }
  },
  {
   "economy": "Malaysia",
   "pillar": "6",
   "run": "outputs/final_ma_p6",
   "gold_indicator": "P6-I4",
   "act": "Personal Data Protection Code of Practice For Banking Sector And Financial Institutions 2017",
   "ref": "s. 1.1",
   "base": "s. 1.1",
   "class": "MAPPING",
   "emitted_under": [],
   "proposed_verdict": "LEGAL_MAPPING_REVIEW",
   "evidence": {
    "corpus_checked": true,
    "matched_output_rows": 0,
    "technical_class": "IN_CORPUS_NOT_EMITTED",
    "failure_taxonomy": "MAPPING"
   },
   "reviewer_verdict": "CORRECT_ABSTENTION",
   "reviewer_note": "CoP clause 1.1 is introductory/definitions material, not operative transfer evidence; engine abstention correct.",
   "recall_key": "76c478364997b00ca629854e6b1890ee01c7de0ccc023ddb2069419eedb7eb5c",
   "review": {
    "recall_key": "76c478364997b00ca629854e6b1890ee01c7de0ccc023ddb2069419eedb7eb5c",
    "verdict": "CORRECT_ABSTENTION",
    "reviewer_name": "Abu Naser Md. Nafew",
    "reviewer_role": "Team Lead, Team zAI BD",
    "reviewed_at": "2026-07-19T12:50:04+00:00",
    "note": "CoP clause 1.1 is introductory/definitions material, not operative transfer evidence; engine abstention correct."
   }
  },
  {
   "economy": "Malaysia",
   "pillar": "6",
   "run": "outputs/final_ma_p6",
   "gold_indicator": "P6-I4",
   "act": "Personal Data Protection Code of Practice For Banking Sector And Financial Institutions 2017",
   "ref": "Sch. 1",
   "base": "sch. 1",
   "class": "STRUCTURE",
   "emitted_under": [],
   "proposed_verdict": "REAL_MISS",
   "evidence": {
    "corpus_checked": true,
    "matched_output_rows": 0,
    "technical_class": "NOT_IN_CORPUS",
    "failure_taxonomy": "STRUCTURE"
   },
   "reviewer_verdict": "REAL_MISS",
   "reviewer_note": "Engine-side gap (mapping/parse/acquisition per technical class); targeted in the 19 Jul night rerun.",
   "recall_key": "f06d2ed93e4e4a97e23c4c9371835b311e5e82fed6b4f60690eea7dbc82232e4",
   "review": {
    "recall_key": "f06d2ed93e4e4a97e23c4c9371835b311e5e82fed6b4f60690eea7dbc82232e4",
    "verdict": "REAL_MISS",
    "reviewer_name": "Abu Naser Md. Nafew",
    "reviewer_role": "Team Lead, Team zAI BD",
    "reviewed_at": "2026-07-19T12:50:04+00:00",
    "note": "Engine-side gap (mapping/parse/acquisition per technical class); targeted in the 19 Jul night rerun."
   }
  },
  {
   "economy": "Malaysia",
   "pillar": "6",
   "run": "outputs/final_ma_p6",
   "gold_indicator": "P6-I4",
   "act": "Personal Data Protection Code of Practice for Licensees Under the Communications and Multimedia (Act 1998) of 2017",
   "ref": "s. 4.7",
   "base": "s. 4.7",
   "class": "STRUCTURE",
   "emitted_under": [],
   "proposed_verdict": "REAL_MISS",
   "evidence": {
    "corpus_checked": true,
    "matched_output_rows": 0,
    "technical_class": "NOT_IN_CORPUS",
    "failure_taxonomy": "STRUCTURE"
   },
   "reviewer_verdict": "REAL_MISS",
   "reviewer_note": "Engine-side gap (mapping/parse/acquisition per technical class); targeted in the 19 Jul night rerun.",
   "recall_key": "3b0bfccc641c3b94e72268baa528d0424369f84497623618a66aa98cdb6d3779",
   "review": {
    "recall_key": "3b0bfccc641c3b94e72268baa528d0424369f84497623618a66aa98cdb6d3779",
    "verdict": "REAL_MISS",
    "reviewer_name": "Abu Naser Md. Nafew",
    "reviewer_role": "Team Lead, Team zAI BD",
    "reviewed_at": "2026-07-19T12:50:04+00:00",
    "note": "Engine-side gap (mapping/parse/acquisition per technical class); targeted in the 19 Jul night rerun."
   }
  },
  {
   "economy": "Malaysia",
   "pillar": "6",
   "run": "outputs/final_ma_p6",
   "gold_indicator": "P6-I4",
   "act": "Personal Data Protection Code of Practice for Licensees Under the Communications and Multimedia (Act 1998) of 2017",
   "ref": "s. 3.2(ii)",
   "base": "s. 3.2",
   "class": "STRUCTURE",
   "emitted_under": [],
   "proposed_verdict": "REAL_MISS",
   "evidence": {
    "corpus_checked": true,
    "matched_output_rows": 0,
    "technical_class": "NOT_IN_CORPUS",
    "failure_taxonomy": "STRUCTURE"
   },
   "reviewer_verdict": "REAL_MISS",
   "reviewer_note": "Engine-side gap (mapping/parse/acquisition per technical class); targeted in the 19 Jul night rerun.",
   "recall_key": "127c22eff8ab6688dc4ff6c4a4ba8368b772b10ee8eb8ce68c86ff76c875ed4e",
   "review": {
    "recall_key": "127c22eff8ab6688dc4ff6c4a4ba8368b772b10ee8eb8ce68c86ff76c875ed4e",
    "verdict": "REAL_MISS",
    "reviewer_name": "Abu Naser Md. Nafew",
    "reviewer_role": "Team Lead, Team zAI BD",
    "reviewed_at": "2026-07-19T12:50:04+00:00",
    "note": "Engine-side gap (mapping/parse/acquisition per technical class); targeted in the 19 Jul night rerun."
   }
  },
  {
   "economy": "Malaysia",
   "pillar": "7",
   "run": "outputs/final_ma_p7",
   "gold_indicator": "P7-I5",
   "act": "Personal Data Protection Code of Practice for Licensees Under the Communications and Multimedia (Act 1998) of 2017",
   "ref": "s. 7.4",
   "base": "s. 7.4",
   "class": "STRUCTURE",
   "emitted_under": [],
   "proposed_verdict": "REAL_MISS",
   "evidence": {
    "corpus_checked": true,
    "matched_output_rows": 0,
    "technical_class": "NOT_IN_CORPUS",
    "failure_taxonomy": "STRUCTURE"
   },
   "reviewer_verdict": "REAL_MISS",
   "reviewer_note": "Engine-side gap (mapping/parse/acquisition per technical class); targeted in the 19 Jul night rerun.",
   "recall_key": "905e485c7f68ef136f82332cc333174129ce13b513601594a6ab2695f0d32a8d",
   "review": {
    "recall_key": "905e485c7f68ef136f82332cc333174129ce13b513601594a6ab2695f0d32a8d",
    "verdict": "REAL_MISS",
    "reviewer_name": "Abu Naser Md. Nafew",
    "reviewer_role": "Team Lead, Team zAI BD",
    "reviewed_at": "2026-07-19T12:50:04+00:00",
    "note": "Engine-side gap (mapping/parse/acquisition per technical class); targeted in the 19 Jul night rerun."
   }
  }
 ]
}